{
  "type": "FeatureCollection",
  "name": "Elixir users",

  "features": [

    {
      "type": "Feature",
      "geometry": {
        "type": "Point",
        "coordinates": [12.9667, 77.5667]
      },
      "properties": {
        "github": "HashNuke"
      }
    }

  ]
}